LICENSE.txt
README.md
__init__.py
conftest.py
libtbx_refresh.py
pyproject.toml
setup.py
command_line/__init__.py
command_line/debug_memory.py
command_line/depends_on.py
command_line/detector_superpose.py
command_line/display_parallax_correction.py
command_line/dlsnxs2cbf.py
command_line/image2pickle.py
command_line/image_average.py
command_line/install_format.py
command_line/overload.py
command_line/plot_detector_models.py
command_line/print_header.py
command_line/print_matching_images.py
command_line/radial_average.py
command_line/read_sequence.py
command_line/saturation.py
command_line/show_matching_formats.py
command_line/show_registry.py
data/__init__.py
data/beamline_defs/PILATUS_2M_S_N_24_0107_Diamond.py
data/beamline_defs/PILATUS_300K_S_N_3_0104_Diamond.py
data/beamline_defs/__init__.py
dxtbx.egg-info/PKG-INFO
dxtbx.egg-info/SOURCES.txt
dxtbx.egg-info/dependency_links.txt
dxtbx.egg-info/not-zip-safe
dxtbx.egg-info/requires.txt
dxtbx.egg-info/top_level.txt
format/Format.py
format/FormatBruker.py
format/FormatBrukerFixedChi.py
format/FormatBrukerPhotonII.py
format/FormatCBF.py
format/FormatCBFCspad.py
format/FormatCBFFull.py
format/FormatCBFFullPilatus.py
format/FormatCBFFullPilatusDLS300KSN104.py
format/FormatCBFFullPilatusDLS6MSN100.py
format/FormatCBFFullPilatusDLS6MSN126.py
format/FormatCBFMini.py
format/FormatCBFMiniADSCHF4M.py
format/FormatCBFMiniEiger.py
format/FormatCBFMiniEigerDLS16MSN160.py
format/FormatCBFMiniEigerMaxIVBio.py
format/FormatCBFMiniEigerPetraP14.py
format/FormatCBFMiniEigerPhotonFactory.py
format/FormatCBFMiniPilatus.py
format/FormatCBFMiniPilatus3APS19ID6MSN132.py
format/FormatCBFMiniPilatusCHESS_6MSN127.py
format/FormatCBFMiniPilatusDESY6MSN115.py
format/FormatCBFMiniPilatusDLS12M.py
format/FormatCBFMiniPilatusDLS6MSN100.py
format/FormatCBFMiniPilatusDLS6MSN114.py
format/FormatCBFMiniPilatusDLS6MSN114DMM.py
format/FormatCBFMiniPilatusDLS6MSN119.py
format/FormatCBFMiniPilatusDLS6MSN126.py
format/FormatCBFMiniPilatusHelpers.py
format/FormatCBFMiniPilatusSOLEILPX16MSN106.py
format/FormatCBFMiniPilatusSPring8_6MSN125.py
format/FormatCBFMiniPilatusXXX.py
format/FormatCBFMultiTile.py
